pyroapi/__init__.py
pyroapi/dispatch.py
pyroapi/testing.py
pyroapi/version.py
pyroapi/tests/__init__.py
pyroapi/tests/test_svi.py
pyro_api-0.1.2.dist-info/LICENSE.md
pyro_api-0.1.2.dist-info/METADATA
pyro_api-0.1.2.dist-info/WHEEL
pyro_api-0.1.2.dist-info/top_level.txt
pyro_api-0.1.2.dist-info/RECORD
