Metadata-Version: 2.1
Name: pyro-api
Version: 0.1.2
Summary: Generic API for dispatch to Pyro backends.
Home-page: https://github.com/pyro-ppl/pyro-api
Author: Uber AI Labs
Author-email: npradhan@uber.com
License: Apache License 2.0
Keywords: probabilistic machine learning bayesian statistics
Platform: UNKNOWN
Classifier: Intended Audience :: Developers
Classifier: Intended Audience :: Education
Classifier: Intended Audience :: Science/Research
Classifier: License :: OSI Approved :: Apache Software License
Classifier: Operating System :: POSIX :: Linux
Classifier: Operating System :: MacOS :: MacOS X
Classifier: Programming Language :: Python :: 3.6
Provides-Extra: test
Provides-Extra: dev
